[
  {
    "Type": "Texture2D",
    "Name": "T_AF_BODY_045_100_D",
    "Class": "UScriptClass'Texture2D'",
    "Properties": {
      "ImportedSize": {
        "X": 2048,
        "Y": 2048
      },
      "LightingGuid": "0EF611F7-459C8187-4ADF1D8E-C1AB9CC1",
      "LODGroup": "TEXTUREGROUP_Project11",
      "NeverStream": true
    },
    "SizeX": 2048,
    "SizeY": 2048,
    "PackedData": 1,
    "PixelFormat": "PF_DXT1",
    "FirstMipToSerialize": 0,
    "Mips": [
      {
        "BulkData": {
          "BulkDataFlags": "BULKDATA_SingleUse | BULKDATA_ForceInlinePayload",
          "ElementCount": 2097152,
          "SizeOnDisk": 2097152,
          "OffsetInFile": "0x2008C2"
        },
        "SizeX": 2048,
        "SizeY": 2048,
        "SizeZ": 1
      }
    ]
  }
]