[
  {
    "Type": "SGANSActionCameraSetting",
    "Name": "SGANSActionCameraSetting_0",
    "Outer": "VGActionEvent_11",
    "Class": "UScriptClass'SGANSActionCameraSetting'",
    "Properties": {
      "m_camera_fov_y": 65.0,
      "m_camera_fov_y_lerp": 0.15
    }
  },
  {
    "Type": "SGANSActionHomingRotation",
    "Name": "SGANSActionHomingRotation_0",
    "Outer": "VGActionEvent_0",
    "Class": "UScriptClass'SGANSActionHomingRotation'",
    "Properties": {
      "m_target_range": 800.0,
      "m_target_rotate_yaw": 90.0,
      "m_rotate_degree_second": 180.0
    }
  },
  {
    "Type": "SGANSActionHomingRotation",
    "Name": "SGANSActionHomingRotation_0",
    "Outer": "VGActionEvent_6",
    "Class": "UScriptClass'SGANSActionHomingRotation'",
    "Properties": {
      "m_is_camlock_only": true,
      "m_is_camlock_only_not_homing": false,
      "m_rotate_degree_second": 2000.0
    }
  },
  {
    "Type": "SGANSActionMovement",
    "Name": "SGANSActionMovement_0",
    "Outer": "VGActionEvent_16",
    "Class": "UScriptClass'SGANSActionMovement'",
    "Properties": {
      "move_value": {
        "X": 250.0,
        "Y": 0.0,
        "Z": 0.0
      },
      "cancel_move_distance": 250.0
    }
  },
  {
    "Type": "SGANSSkillActionBranch",
    "Name": "SGANSSkillActionBranch_0",
    "Outer": "VGActionEvent_41",
    "Class": "UScriptClass'SGANSSkillActionBranch'",
    "Properties": {
      "early_frame": 15,
      "early_time": 0.5
    }
  },
  {
    "Type": "SGANSWeaponSkillEmissive",
    "Name": "SGANSWeaponSkillEmissive_0",
    "Outer": "VGActionEvent_18",
    "Class": "UScriptClass'SGANSWeaponSkillEmissive'",
    "Properties": {
      "fade_time": 0.5
    }
  },
  {
    "Type": "VGActionAsset",
    "Name": "ACT_SWD3_SKL_006_Air",
    "Class": "UScriptClass'VGActionAsset'",
    "Properties": {
      "name": "SKL_SWD3_006_Air",
      "action_id": 12051,
      "states": [
        "EVGActionState::Attack",
        "EVGActionState::WeaponAction",
        "EVGActionState::Air"
      ],
      "anim_assets": {
        "animation": {
          "ObjectName": "AnimMontage'MNT_SWD3_SKL_006_Air'",
          "ObjectPath": "/Game/Product/Character/Human/Common/Animation/Montage/SWD3/MNT_SWD3_SKL_006_Air.0"
        }
      },
      "action_events": [
        {
          "ObjectName": "VGActionEvent'ACT_SWD3_SKL_006_Air:VGActionEvent_3'",
          "ObjectPath": "/Game/Product/Character/Human/Common/Action/SWD3/SWD3_SKL/ACT_SWD3_SKL_006_Air.20"
        },
        {
          "ObjectName": "VGActionEvent'ACT_SWD3_SKL_006_Air:VGActionEvent_15'",
          "ObjectPath": "/Game/Product/Character/Human/Common/Action/SWD3/SWD3_SKL/ACT_SWD3_SKL_006_Air.12"
        },
        {
          "ObjectName": "VGActionEvent'ACT_SWD3_SKL_006_Air:VGActionEvent_46'",
          "ObjectPath": "/Game/Product/Character/Human/Common/Action/SWD3/SWD3_SKL/ACT_SWD3_SKL_006_Air.32"
        },
        {
          "ObjectName": "VGActionEvent'ACT_SWD3_SKL_006_Air:VGActionEvent_0'",
          "ObjectPath": "/Game/Product/Character/Human/Common/Action/SWD3/SWD3_SKL/ACT_SWD3_SKL_006_Air.7"
        },
        {
          "ObjectName": "VGActionEvent'ACT_SWD3_SKL_006_Air:VGActionEvent_6'",
          "ObjectPath": "/Game/Product/Character/Human/Common/Action/SWD3/SWD3_SKL/ACT_SWD3_SKL_006_Air.35"
        },
        {
          "ObjectName": "VGActionEvent'ACT_SWD3_SKL_006_Air:VGActionEvent_1'",
          "ObjectPath": "/Game/Product/Character/Human/Common/Action/SWD3/SWD3_SKL/ACT_SWD3_SKL_006_Air.8"
        },
        {
          "ObjectName": "VGActionEvent'ACT_SWD3_SKL_006_Air:VGActionEvent_41'",
          "ObjectPath": "/Game/Product/Character/Human/Common/Action/SWD3/SWD3_SKL/ACT_SWD3_SKL_006_Air.28"
        },
        {
          "ObjectName": "VGActionEvent'ACT_SWD3_SKL_006_Air:VGActionEvent_48'",
          "ObjectPath": "/Game/Product/Character/Human/Common/Action/SWD3/SWD3_SKL/ACT_SWD3_SKL_006_Air.33"
        },
        {
          "ObjectName": "VGActionEvent'ACT_SWD3_SKL_006_Air:VGActionEvent_45'",
          "ObjectPath": "/Game/Product/Character/Human/Common/Action/SWD3/SWD3_SKL/ACT_SWD3_SKL_006_Air.31"
        },
        {
          "ObjectName": "VGActionEvent'ACT_SWD3_SKL_006_Air:VGActionEvent_16'",
          "ObjectPath": "/Game/Product/Character/Human/Common/Action/SWD3/SWD3_SKL/ACT_SWD3_SKL_006_Air.13"
        },
        {
          "ObjectName": "VGActionEvent'ACT_SWD3_SKL_006_Air:VGActionEvent_43'",
          "ObjectPath": "/Game/Product/Character/Human/Common/Action/SWD3/SWD3_SKL/ACT_SWD3_SKL_006_Air.29"
        },
        {
          "ObjectName": "VGActionEvent'ACT_SWD3_SKL_006_Air:VGActionEvent_39'",
          "ObjectPath": "/Game/Product/Character/Human/Common/Action/SWD3/SWD3_SKL/ACT_SWD3_SKL_006_Air.26"
        },
        {
          "ObjectName": "VGActionEvent'ACT_SWD3_SKL_006_Air:VGActionEvent_38'",
          "ObjectPath": "/Game/Product/Character/Human/Common/Action/SWD3/SWD3_SKL/ACT_SWD3_SKL_006_Air.25"
        },
        {
          "ObjectName": "VGActionEvent'ACT_SWD3_SKL_006_Air:VGActionEvent_19'",
          "ObjectPath": "/Game/Product/Character/Human/Common/Action/SWD3/SWD3_SKL/ACT_SWD3_SKL_006_Air.15"
        },
        {
          "ObjectName": "VGActionEvent'ACT_SWD3_SKL_006_Air:VGActionEvent_49'",
          "ObjectPath": "/Game/Product/Character/Human/Common/Action/SWD3/SWD3_SKL/ACT_SWD3_SKL_006_Air.34"
        },
        {
          "ObjectName": "VGActionEvent'ACT_SWD3_SKL_006_Air:VGActionEvent_30'",
          "ObjectPath": "/Game/Product/Character/Human/Common/Action/SWD3/SWD3_SKL/ACT_SWD3_SKL_006_Air.21"
        },
        {
          "ObjectName": "VGActionEvent'ACT_SWD3_SKL_006_Air:VGActionEvent_21'",
          "ObjectPath": "/Game/Product/Character/Human/Common/Action/SWD3/SWD3_SKL/ACT_SWD3_SKL_006_Air.17"
        },
        {
          "ObjectName": "VGActionEvent'ACT_SWD3_SKL_006_Air:VGActionEvent_34'",
          "ObjectPath": "/Game/Product/Character/Human/Common/Action/SWD3/SWD3_SKL/ACT_SWD3_SKL_006_Air.24"
        },
        {
          "ObjectName": "VGActionEvent'ACT_SWD3_SKL_006_Air:VGActionEvent_11'",
          "ObjectPath": "/Game/Product/Character/Human/Common/Action/SWD3/SWD3_SKL/ACT_SWD3_SKL_006_Air.9"
        }
      ],
      "post_phys_events": [
        {
          "ObjectName": "VGActionEvent'ACT_SWD3_SKL_006_Air:VGActionEvent_18'",
          "ObjectPath": "/Game/Product/Character/Human/Common/Action/SWD3/SWD3_SKL/ACT_SWD3_SKL_006_Air.14"
        },
        {
          "ObjectName": "VGActionEvent'ACT_SWD3_SKL_006_Air:VGActionEvent_67'",
          "ObjectPath": "/Game/Product/Character/Human/Common/Action/SWD3/SWD3_SKL/ACT_SWD3_SKL_006_Air.36"
        },
        {
          "ObjectName": "VGActionEvent'ACT_SWD3_SKL_006_Air:VGActionEvent_13'",
          "ObjectPath": "/Game/Product/Character/Human/Common/Action/SWD3/SWD3_SKL/ACT_SWD3_SKL_006_Air.10"
        },
        {
          "ObjectName": "VGActionEvent'ACT_SWD3_SKL_006_Air:VGActionEvent_14'",
          "ObjectPath": "/Game/Product/Character/Human/Common/Action/SWD3/SWD3_SKL/ACT_SWD3_SKL_006_Air.11"
        },
        {
          "ObjectName": "VGActionEvent'ACT_SWD3_SKL_006_Air:VGActionEvent_31'",
          "ObjectPath": "/Game/Product/Character/Human/Common/Action/SWD3/SWD3_SKL/ACT_SWD3_SKL_006_Air.22"
        },
        {
          "ObjectName": "VGActionEvent'ACT_SWD3_SKL_006_Air:VGActionEvent_4'",
          "ObjectPath": "/Game/Product/Character/Human/Common/Action/SWD3/SWD3_SKL/ACT_SWD3_SKL_006_Air.27"
        },
        {
          "ObjectName": "VGActionEvent'ACT_SWD3_SKL_006_Air:VGActionEvent_2'",
          "ObjectPath": "/Game/Product/Character/Human/Common/Action/SWD3/SWD3_SKL/ACT_SWD3_SKL_006_Air.16"
        },
        {
          "ObjectName": "VGActionEvent'ACT_SWD3_SKL_006_Air:VGActionEvent_9'",
          "ObjectPath": "/Game/Product/Character/Human/Common/Action/SWD3/SWD3_SKL/ACT_SWD3_SKL_006_Air.37"
        },
        {
          "ObjectName": "VGActionEvent'ACT_SWD3_SKL_006_Air:VGActionEvent_33'",
          "ObjectPath": "/Game/Product/Character/Human/Common/Action/SWD3/SWD3_SKL/ACT_SWD3_SKL_006_Air.23"
        },
        {
          "ObjectName": "VGActionEvent'ACT_SWD3_SKL_006_Air:VGActionEvent_22'",
          "ObjectPath": "/Game/Product/Character/Human/Common/Action/SWD3/SWD3_SKL/ACT_SWD3_SKL_006_Air.18"
        },
        {
          "ObjectName": "VGActionEvent'ACT_SWD3_SKL_006_Air:VGActionEvent_23'",
          "ObjectPath": "/Game/Product/Character/Human/Common/Action/SWD3/SWD3_SKL/ACT_SWD3_SKL_006_Air.19"
        },
        {
          "ObjectName": "VGActionEvent'ACT_SWD3_SKL_006_Air:VGActionEvent_44'",
          "ObjectPath": "/Game/Product/Character/Human/Common/Action/SWD3/SWD3_SKL/ACT_SWD3_SKL_006_Air.30"
        }
      ]
    }
  },
  {
    "Type": "VGActionEvent",
    "Name": "VGActionEvent_0",
    "Outer": "ACT_SWD3_SKL_006_Air",
    "Class": "UScriptClass'VGActionEvent'",
    "Properties": {
      "event_name": "ノーロック時",
      "num_frames": 4,
      "end_time": 0.13333334,
      "notify_state": {
        "ObjectName": "SGANSActionHomingRotation'ACT_SWD3_SKL_006_Air:VGActionEvent_0.SGANSActionHomingRotation_0'",
        "ObjectPath": "/Game/Product/Character/Human/Common/Action/SWD3/SWD3_SKL/ACT_SWD3_SKL_006_Air.1"
      }
    }
  },
  {
    "Type": "VGActionEvent",
    "Name": "VGActionEvent_1",
    "Outer": "ACT_SWD3_SKL_006_Air",
    "Class": "UScriptClass'VGActionEvent'",
    "Properties": {
      "event_name": "地上付近だったら地上版",
      "num_frames": 2,
      "end_time": 0.06666667,
      "notify_state": {
        "ObjectName": "VGANSActionBranch'ACT_SWD3_SKL_006_Air:VGActionEvent_1.VGANSActionBranch_0'",
        "ObjectPath": "/Game/Product/Character/Human/Common/Action/SWD3/SWD3_SKL/ACT_SWD3_SKL_006_Air.49"
      }
    }
  },
  {
    "Type": "VGActionEvent",
    "Name": "VGActionEvent_11",
    "Outer": "ACT_SWD3_SKL_006_Air",
    "Class": "UScriptClass'VGActionEvent'",
    "Properties": {
      "event_name": "カメラズーム",
      "start_frame": 5,
      "num_frames": 28,
      "start_time": 0.16666667,
      "end_time": 1.1,
      "notify_state": {
        "ObjectName": "SGANSActionCameraSetting'ACT_SWD3_SKL_006_Air:VGActionEvent_11.SGANSActionCameraSetting_0'",
        "ObjectPath": "/Game/Product/Character/Human/Common/Action/SWD3/SWD3_SKL/ACT_SWD3_SKL_006_Air.0"
      }
    }
  },
  {
    "Type": "VGActionEvent",
    "Name": "VGActionEvent_13",
    "Outer": "ACT_SWD3_SKL_006_Air",
    "Class": "UScriptClass'VGActionEvent'",
    "Properties": {
      "event_name": "攻撃時ボイス",
      "start_frame": 19,
      "start_time": 0.6333334,
      "end_time": 0.66666675,
      "notify": {
        "ObjectName": "VGANPlaySound'ACT_SWD3_SKL_006_Air:VGActionEvent_13.VGANPlaySound_0'",
        "ObjectPath": "/Game/Product/Character/Human/Common/Action/SWD3/SWD3_SKL/ACT_SWD3_SKL_006_Air.41"
      }
    }
  },
  {
    "Type": "VGActionEvent",
    "Name": "VGActionEvent_14",
    "Outer": "ACT_SWD3_SKL_006_Air",
    "Class": "UScriptClass'VGActionEvent'",
    "Properties": {
      "event_name": "構え音",
      "start_frame": 5,
      "start_time": 0.16666667,
      "end_time": 0.2,
      "notify": {
        "ObjectName": "VGANPlaySound'ACT_SWD3_SKL_006_Air:VGActionEvent_14.VGANPlaySound_0'",
        "ObjectPath": "/Game/Product/Character/Human/Common/Action/SWD3/SWD3_SKL/ACT_SWD3_SKL_006_Air.42"
      }
    }
  },
  {
    "Type": "VGActionEvent",
    "Name": "VGActionEvent_15",
    "Outer": "ACT_SWD3_SKL_006_Air",
    "Class": "UScriptClass'VGActionEvent'",
    "Properties": {
      "event_name": "重力無視",
      "start_frame": 2,
      "num_frames": 19,
      "start_time": 0.06666667,
      "end_time": 0.70000005,
      "notify_state": {
        "ObjectName": "VGANSActionState'ACT_SWD3_SKL_006_Air:VGActionEvent_15.VGANSActionState_0'",
        "ObjectPath": "/Game/Product/Character/Human/Common/Action/SWD3/SWD3_SKL/ACT_SWD3_SKL_006_Air.55"
      }
    }
  },
  {
    "Type": "VGActionEvent",
    "Name": "VGActionEvent_16",
    "Outer": "ACT_SWD3_SKL_006_Air",
    "Class": "UScriptClass'VGActionEvent'",
    "Properties": {
      "start_frame": 7,
      "num_frames": 5,
      "start_time": 0.23333335,
      "end_time": 0.40000004,
      "notify_state": {
        "ObjectName": "SGANSActionMovement'ACT_SWD3_SKL_006_Air:VGActionEvent_16.SGANSActionMovement_0'",
        "ObjectPath": "/Game/Product/Character/Human/Common/Action/SWD3/SWD3_SKL/ACT_SWD3_SKL_006_Air.3"
      }
    }
  },
  {
    "Type": "VGActionEvent",
    "Name": "VGActionEvent_18",
    "Outer": "ACT_SWD3_SKL_006_Air",
    "Class": "UScriptClass'VGActionEvent'",
    "Properties": {
      "start_frame": 3,
      "num_frames": 26,
      "start_time": 0.10000001,
      "end_time": 0.96666676,
      "notify_state": {
        "ObjectName": "SGANSWeaponSkillEmissive'ACT_SWD3_SKL_006_Air:VGActionEvent_18.SGANSWeaponSkillEmissive_0'",
        "ObjectPath": "/Game/Product/Character/Human/Common/Action/SWD3/SWD3_SKL/ACT_SWD3_SKL_006_Air.5"
      }
    }
  },
  {
    "Type": "VGActionEvent",
    "Name": "VGActionEvent_19",
    "Outer": "ACT_SWD3_SKL_006_Air",
    "Class": "UScriptClass'VGActionEvent'",
    "Properties": {
      "event_name": "回転1",
      "start_frame": 14,
      "num_frames": 2,
      "start_time": 0.4666667,
      "end_time": 0.53333336,
      "notify_state": {
        "ObjectName": "VGANSWeaponAttack'ACT_SWD3_SKL_006_Air:VGActionEvent_19.VGANSWeaponAttack_0'",
        "ObjectPath": "/Game/Product/Character/Human/Common/Action/SWD3/SWD3_SKL/ACT_SWD3_SKL_006_Air.61"
      }
    }
  },
  {
    "Type": "VGActionEvent",
    "Name": "VGActionEvent_2",
    "Outer": "ACT_SWD3_SKL_006_Air",
    "Class": "UScriptClass'VGActionEvent'",
    "Properties": {
      "event_name": "風切り音",
      "start_frame": 19,
      "start_time": 0.6333334,
      "end_time": 0.66666675,
      "notify": {
        "ObjectName": "VGANPlaySound'ACT_SWD3_SKL_006_Air:VGActionEvent_2.VGANPlaySound_0'",
        "ObjectPath": "/Game/Product/Character/Human/Common/Action/SWD3/SWD3_SKL/ACT_SWD3_SKL_006_Air.43"
      }
    }
  },
  {
    "Type": "VGActionEvent",
    "Name": "VGActionEvent_21",
    "Outer": "ACT_SWD3_SKL_006_Air",
    "Class": "UScriptClass'VGActionEvent'",
    "Properties": {
      "event_name": "打ち上げ",
      "start_frame": 22,
      "num_frames": 3,
      "start_time": 0.73333335,
      "end_time": 0.8333334,
      "notify_state": {
        "ObjectName": "VGANSWeaponAttack'ACT_SWD3_SKL_006_Air:VGActionEvent_21.VGANSWeaponAttack_0'",
        "ObjectPath": "/Game/Product/Character/Human/Common/Action/SWD3/SWD3_SKL/ACT_SWD3_SKL_006_Air.62"
      }
    }
  },
  {
    "Type": "VGActionEvent",
    "Name": "VGActionEvent_22",
    "Outer": "ACT_SWD3_SKL_006_Air",
    "Class": "UScriptClass'VGActionEvent'",
    "Properties": {
      "event_name": "軌跡",
      "start_frame": 11,
      "start_time": 0.36666667,
      "end_time": 0.4,
      "notify": {
        "ObjectName": "VGANSignalVfx'ACT_SWD3_SKL_006_Air:VGActionEvent_22.VGANSignalVfx_0'",
        "ObjectPath": "/Game/Product/Character/Human/Common/Action/SWD3/SWD3_SKL/ACT_SWD3_SKL_006_Air.58"
      }
    }
  },
  {
    "Type": "VGActionEvent",
    "Name": "VGActionEvent_23",
    "Outer": "ACT_SWD3_SKL_006_Air",
    "Class": "UScriptClass'VGActionEvent'",
    "Properties": {
      "event_name": "軌跡",
      "start_frame": 14,
      "start_time": 0.4666667,
      "end_time": 0.50000006,
      "notify": {
        "ObjectName": "VGANSignalVfx'ACT_SWD3_SKL_006_Air:VGActionEvent_23.VGANSignalVfx_0'",
        "ObjectPath": "/Game/Product/Character/Human/Common/Action/SWD3/SWD3_SKL/ACT_SWD3_SKL_006_Air.59"
      }
    }
  },
  {
    "Type": "VGActionEvent",
    "Name": "VGActionEvent_3",
    "Outer": "ACT_SWD3_SKL_006_Air",
    "Class": "UScriptClass'VGActionEvent'",
    "Properties": {
      "num_frames": 46,
      "end_time": 1.5333334,
      "notify_state": {
        "ObjectName": "VGANSActionState'ACT_SWD3_SKL_006_Air:VGActionEvent_3.VGANSActionState_0'",
        "ObjectPath": "/Game/Product/Character/Human/Common/Action/SWD3/SWD3_SKL/ACT_SWD3_SKL_006_Air.56"
      }
    }
  },
  {
    "Type": "VGActionEvent",
    "Name": "VGActionEvent_30",
    "Outer": "ACT_SWD3_SKL_006_Air",
    "Class": "UScriptClass'VGActionEvent'",
    "Properties": {
      "start_frame": 13,
      "start_time": 0.43333337,
      "end_time": 0.4666667,
      "notify": {
        "ObjectName": "VGANCameraShake'ACT_SWD3_SKL_006_Air:VGActionEvent_30.VGANCameraShake_0'",
        "ObjectPath": "/Game/Product/Character/Human/Common/Action/SWD3/SWD3_SKL/ACT_SWD3_SKL_006_Air.38"
      }
    }
  },
  {
    "Type": "VGActionEvent",
    "Name": "VGActionEvent_31",
    "Outer": "ACT_SWD3_SKL_006_Air",
    "Class": "UScriptClass'VGActionEvent'",
    "Properties": {
      "event_name": "風切り音",
      "start_frame": 10,
      "start_time": 0.33333334,
      "end_time": 0.36666667,
      "notify": {
        "ObjectName": "VGANPlaySound'ACT_SWD3_SKL_006_Air:VGActionEvent_31.VGANPlaySound_0'",
        "ObjectPath": "/Game/Product/Character/Human/Common/Action/SWD3/SWD3_SKL/ACT_SWD3_SKL_006_Air.44"
      }
    }
  },
  {
    "Type": "VGActionEvent",
    "Name": "VGActionEvent_33",
    "Outer": "ACT_SWD3_SKL_006_Air",
    "Class": "UScriptClass'VGActionEvent'",
    "Properties": {
      "event_name": "構え直し音",
      "start_frame": 43,
      "start_time": 1.4333334,
      "end_time": 1.4666667,
      "notify": {
        "ObjectName": "VGANPlaySound'ACT_SWD3_SKL_006_Air:VGActionEvent_33.VGANPlaySound_0'",
        "ObjectPath": "/Game/Product/Character/Human/Common/Action/SWD3/SWD3_SKL/ACT_SWD3_SKL_006_Air.45"
      }
    }
  },
  {
    "Type": "VGActionEvent",
    "Name": "VGActionEvent_34",
    "Outer": "ACT_SWD3_SKL_006_Air",
    "Class": "UScriptClass'VGActionEvent'",
    "Properties": {
      "start_frame": 21,
      "start_time": 0.70000005,
      "end_time": 0.7333334,
      "notify": {
        "ObjectName": "VGANCameraShake'ACT_SWD3_SKL_006_Air:VGActionEvent_34.VGANCameraShake_0'",
        "ObjectPath": "/Game/Product/Character/Human/Common/Action/SWD3/SWD3_SKL/ACT_SWD3_SKL_006_Air.39"
      }
    }
  },
  {
    "Type": "VGActionEvent",
    "Name": "VGActionEvent_38",
    "Outer": "ACT_SWD3_SKL_006_Air",
    "Class": "UScriptClass'VGActionEvent'",
    "Properties": {
      "event_name": "落下を速く",
      "start_frame": 33,
      "start_time": 1.1,
      "end_time": 1.1333333,
      "notify_state": {
        "ObjectName": "VGANSActionMovement'ACT_SWD3_SKL_006_Air:VGActionEvent_38.VGANSActionMovement_0'",
        "ObjectPath": "/Game/Product/Character/Human/Common/Action/SWD3/SWD3_SKL/ACT_SWD3_SKL_006_Air.52"
      }
    }
  },
  {
    "Type": "VGActionEvent",
    "Name": "VGActionEvent_39",
    "Outer": "ACT_SWD3_SKL_006_Air",
    "Class": "UScriptClass'VGActionEvent'",
    "Properties": {
      "start_frame": 24,
      "num_frames": 4,
      "start_time": 0.8000001,
      "end_time": 0.9333334,
      "notify_state": {
        "ObjectName": "VGANSActionMovement'ACT_SWD3_SKL_006_Air:VGActionEvent_39.VGANSActionMovement_0'",
        "ObjectPath": "/Game/Product/Character/Human/Common/Action/SWD3/SWD3_SKL/ACT_SWD3_SKL_006_Air.53"
      }
    }
  },
  {
    "Type": "VGActionEvent",
    "Name": "VGActionEvent_4",
    "Outer": "ACT_SWD3_SKL_006_Air",
    "Class": "UScriptClass'VGActionEvent'",
    "Properties": {
      "event_name": "風切り音(光剣用)",
      "start_frame": 10,
      "start_time": 0.33333334,
      "end_time": 0.36666667,
      "notify": {
        "ObjectName": "VGANPlaySound'ACT_SWD3_SKL_006_Air:VGActionEvent_4.VGANPlaySound_0'",
        "ObjectPath": "/Game/Product/Character/Human/Common/Action/SWD3/SWD3_SKL/ACT_SWD3_SKL_006_Air.46"
      }
    }
  },
  {
    "Type": "VGActionEvent",
    "Name": "VGActionEvent_41",
    "Outer": "ACT_SWD3_SKL_006_Air",
    "Class": "UScriptClass'VGActionEvent'",
    "Properties": {
      "start_frame": 17,
      "num_frames": 29,
      "start_time": 0.5666667,
      "end_time": 1.5333334,
      "notify_state": {
        "ObjectName": "SGANSSkillActionBranch'ACT_SWD3_SKL_006_Air:VGActionEvent_41.SGANSSkillActionBranch_0'",
        "ObjectPath": "/Game/Product/Character/Human/Common/Action/SWD3/SWD3_SKL/ACT_SWD3_SKL_006_Air.4"
      }
    }
  },
  {
    "Type": "VGActionEvent",
    "Name": "VGActionEvent_43",
    "Outer": "ACT_SWD3_SKL_006_Air",
    "Class": "UScriptClass'VGActionEvent'",
    "Properties": {
      "start_frame": 21,
      "num_frames": 4,
      "start_time": 0.70000005,
      "end_time": 0.8333334,
      "notify_state": {
        "ObjectName": "VGANSActionMovement'ACT_SWD3_SKL_006_Air:VGActionEvent_43.VGANSActionMovement_0'",
        "ObjectPath": "/Game/Product/Character/Human/Common/Action/SWD3/SWD3_SKL/ACT_SWD3_SKL_006_Air.54"
      }
    }
  },
  {
    "Type": "VGActionEvent",
    "Name": "VGActionEvent_44",
    "Outer": "ACT_SWD3_SKL_006_Air",
    "Class": "UScriptClass'VGActionEvent'",
    "Properties": {
      "event_name": "斬り上げ",
      "start_frame": 20,
      "start_time": 0.6666667,
      "end_time": 0.70000005,
      "notify": {
        "ObjectName": "VGANSignalVfx'ACT_SWD3_SKL_006_Air:VGActionEvent_44.VGANSignalVfx_0'",
        "ObjectPath": "/Game/Product/Character/Human/Common/Action/SWD3/SWD3_SKL/ACT_SWD3_SKL_006_Air.60"
      }
    }
  },
  {
    "Type": "VGActionEvent",
    "Name": "VGActionEvent_45",
    "Outer": "ACT_SWD3_SKL_006_Air",
    "Class": "UScriptClass'VGActionEvent'",
    "Properties": {
      "event_name": "落下遷移NC",
      "start_frame": 44,
      "num_frames": 2,
      "start_time": 1.4666667,
      "end_time": 1.5333334,
      "notify_state": {
        "ObjectName": "VGANSActionBranch'ACT_SWD3_SKL_006_Air:VGActionEvent_45.VGANSActionBranch_0'",
        "ObjectPath": "/Game/Product/Character/Human/Common/Action/SWD3/SWD3_SKL/ACT_SWD3_SKL_006_Air.50"
      }
    }
  },
  {
    "Type": "VGActionEvent",
    "Name": "VGActionEvent_46",
    "Outer": "ACT_SWD3_SKL_006_Air",
    "Class": "UScriptClass'VGActionEvent'",
    "Properties": {
      "event_name": "重力無視",
      "start_frame": 26,
      "num_frames": 8,
      "start_time": 0.86666673,
      "end_time": 1.1333334,
      "notify_state": {
        "ObjectName": "VGANSActionState'ACT_SWD3_SKL_006_Air:VGActionEvent_46.VGANSActionState_0'",
        "ObjectPath": "/Game/Product/Character/Human/Common/Action/SWD3/SWD3_SKL/ACT_SWD3_SKL_006_Air.57"
      }
    }
  },
  {
    "Type": "VGActionEvent",
    "Name": "VGActionEvent_48",
    "Outer": "ACT_SWD3_SKL_006_Air",
    "Class": "UScriptClass'VGActionEvent'",
    "Properties": {
      "event_name": "着地遷移（しない）",
      "start_frame": 40,
      "num_frames": 6,
      "start_time": 1.3333334,
      "end_time": 1.5333334,
      "notify_state": {
        "ObjectName": "VGANSActionBranch'ACT_SWD3_SKL_006_Air:VGActionEvent_48.VGANSActionBranch_1'",
        "ObjectPath": "/Game/Product/Character/Human/Common/Action/SWD3/SWD3_SKL/ACT_SWD3_SKL_006_Air.51"
      }
    }
  },
  {
    "Type": "VGActionEvent",
    "Name": "VGActionEvent_49",
    "Outer": "ACT_SWD3_SKL_006_Air",
    "Class": "UScriptClass'VGActionEvent'",
    "Properties": {
      "start_frame": 13,
      "start_time": 0.43333337,
      "end_time": 0.4666667,
      "notify": {
        "ObjectName": "VGANCameraShake'ACT_SWD3_SKL_006_Air:VGActionEvent_49.VGANCameraShake_0'",
        "ObjectPath": "/Game/Product/Character/Human/Common/Action/SWD3/SWD3_SKL/ACT_SWD3_SKL_006_Air.40"
      }
    }
  },
  {
    "Type": "VGActionEvent",
    "Name": "VGActionEvent_6",
    "Outer": "ACT_SWD3_SKL_006_Air",
    "Class": "UScriptClass'VGActionEvent'",
    "Properties": {
      "event_name": "カメラロック時",
      "num_frames": 4,
      "end_time": 0.13333334,
      "notify_state": {
        "ObjectName": "SGANSActionHomingRotation'ACT_SWD3_SKL_006_Air:VGActionEvent_6.SGANSActionHomingRotation_0'",
        "ObjectPath": "/Game/Product/Character/Human/Common/Action/SWD3/SWD3_SKL/ACT_SWD3_SKL_006_Air.2"
      }
    }
  },
  {
    "Type": "VGActionEvent",
    "Name": "VGActionEvent_67",
    "Outer": "ACT_SWD3_SKL_006_Air",
    "Class": "UScriptClass'VGActionEvent'",
    "Properties": {
      "event_name": "発動ボイス",
      "start_frame": 3,
      "start_time": 0.10000001,
      "end_time": 0.13333334,
      "notify": {
        "ObjectName": "VGANPlaySound'ACT_SWD3_SKL_006_Air:VGActionEvent_67.VGANPlaySound_0'",
        "ObjectPath": "/Game/Product/Character/Human/Common/Action/SWD3/SWD3_SKL/ACT_SWD3_SKL_006_Air.47"
      }
    }
  },
  {
    "Type": "VGActionEvent",
    "Name": "VGActionEvent_9",
    "Outer": "ACT_SWD3_SKL_006_Air",
    "Class": "UScriptClass'VGActionEvent'",
    "Properties": {
      "event_name": "風切り音(光剣用)",
      "start_frame": 19,
      "start_time": 0.6333334,
      "end_time": 0.66666675,
      "notify": {
        "ObjectName": "VGANPlaySound'ACT_SWD3_SKL_006_Air:VGActionEvent_9.VGANPlaySound_0'",
        "ObjectPath": "/Game/Product/Character/Human/Common/Action/SWD3/SWD3_SKL/ACT_SWD3_SKL_006_Air.48"
      }
    }
  },
  {
    "Type": "VGANCameraShake",
    "Name": "VGANCameraShake_0",
    "Outer": "VGActionEvent_30",
    "Class": "UScriptClass'VGANCameraShake'",
    "Properties": {
      "shake": {
        "ObjectName": "BlueprintGeneratedClass'VCS_CMN_Weapon_VerticalSwing_C'",
        "ObjectPath": "/Game/Product/Character/Common/CameraShake/VCS_CMN_Weapon_VerticalSwing.0"
      },
      "inner_radius": 0.1,
      "outer_radius": 0.2,
      "is_local_user": true
    }
  },
  {
    "Type": "VGANCameraShake",
    "Name": "VGANCameraShake_0",
    "Outer": "VGActionEvent_34",
    "Class": "UScriptClass'VGANCameraShake'",
    "Properties": {
      "shake": {
        "ObjectName": "BlueprintGeneratedClass'VCS_CMN_Weapon_Middle_C'",
        "ObjectPath": "/Game/Product/Character/Common/CameraShake/VCS_CMN_Weapon_Middle.0"
      },
      "inner_radius": 0.1,
      "outer_radius": 0.2,
      "is_local_user": true
    }
  },
  {
    "Type": "VGANCameraShake",
    "Name": "VGANCameraShake_0",
    "Outer": "VGActionEvent_49",
    "Class": "UScriptClass'VGANCameraShake'",
    "Properties": {
      "shake": {
        "ObjectName": "BlueprintGeneratedClass'VCS_CMN_Weapon_SideSwing2_C'",
        "ObjectPath": "/Game/Product/Character/Common/CameraShake/VCS_CMN_Weapon_SideSwing2.0"
      },
      "inner_radius": 0.1,
      "outer_radius": 0.2,
      "is_local_user": true
    }
  },
  {
    "Type": "VGANPlaySound",
    "Name": "VGANPlaySound_0",
    "Outer": "VGActionEvent_13",
    "Class": "UScriptClass'VGANPlaySound'",
    "Properties": {
      "cue_infos": [
        {
          "SoundType": "EVGSoundType::COMPONENT_VOICE",
          "CueId": 6100,
          "CueName": "",
          "BlockIndex": 0,
          "Volume": 1.0,
          "Pitch": 0.0,
          "AisacParam": [],
          "IsStopForChangedAction": false,
          "IsReportPlayEnd": false,
          "IsPhysicalSurface": false,
          "IsPitchChangeByScale": false,
          "CueSheetIndex": 0
        }
      ],
      "is_attach": true,
      "node_name": "b_C_Base"
    }
  },
  {
    "Type": "VGANPlaySound",
    "Name": "VGANPlaySound_0",
    "Outer": "VGActionEvent_14",
    "Class": "UScriptClass'VGANPlaySound'",
    "Properties": {
      "cue_infos": [
        {
          "SoundType": "EVGSoundType::COMPONENT_SE",
          "CueId": 20700,
          "CueName": "",
          "BlockIndex": 0,
          "Volume": 1.0,
          "Pitch": 0.0,
          "AisacParam": [],
          "IsStopForChangedAction": false,
          "IsReportPlayEnd": false,
          "IsPhysicalSurface": false,
          "IsPitchChangeByScale": false,
          "CueSheetIndex": 0
        }
      ],
      "is_attach": true,
      "node_name": "b_C_Base"
    }
  },
  {
    "Type": "VGANPlaySound",
    "Name": "VGANPlaySound_0",
    "Outer": "VGActionEvent_2",
    "Class": "UScriptClass'VGANPlaySound'",
    "Properties": {
      "cue_infos": [
        {
          "SoundType": "EVGSoundType::COMPONENT_SE",
          "CueId": 20703,
          "CueName": "",
          "BlockIndex": 0,
          "Volume": 1.0,
          "Pitch": 0.0,
          "AisacParam": [],
          "IsStopForChangedAction": false,
          "IsReportPlayEnd": false,
          "IsPhysicalSurface": false,
          "IsPitchChangeByScale": false,
          "CueSheetIndex": 0
        }
      ],
      "is_attach": true,
      "node_name": "b_C_Base"
    }
  },
  {
    "Type": "VGANPlaySound",
    "Name": "VGANPlaySound_0",
    "Outer": "VGActionEvent_31",
    "Class": "UScriptClass'VGANPlaySound'",
    "Properties": {
      "cue_infos": [
        {
          "SoundType": "EVGSoundType::COMPONENT_SE",
          "CueId": 20701,
          "CueName": "",
          "BlockIndex": 0,
          "Volume": 1.0,
          "Pitch": 0.0,
          "AisacParam": [],
          "IsStopForChangedAction": false,
          "IsReportPlayEnd": false,
          "IsPhysicalSurface": false,
          "IsPitchChangeByScale": false,
          "CueSheetIndex": 0
        }
      ],
      "is_attach": true,
      "node_name": "b_C_Base"
    }
  },
  {
    "Type": "VGANPlaySound",
    "Name": "VGANPlaySound_0",
    "Outer": "VGActionEvent_33",
    "Class": "UScriptClass'VGANPlaySound'",
    "Properties": {
      "cue_infos": [
        {
          "SoundType": "EVGSoundType::COMPONENT_SE",
          "CueId": 20704,
          "CueName": "",
          "BlockIndex": 0,
          "Volume": 1.0,
          "Pitch": 0.0,
          "AisacParam": [],
          "IsStopForChangedAction": false,
          "IsReportPlayEnd": false,
          "IsPhysicalSurface": false,
          "IsPitchChangeByScale": false,
          "CueSheetIndex": 0
        }
      ],
      "is_attach": true,
      "node_name": "b_C_Base"
    }
  },
  {
    "Type": "VGANPlaySound",
    "Name": "VGANPlaySound_0",
    "Outer": "VGActionEvent_4",
    "Class": "UScriptClass'VGANPlaySound'",
    "Properties": {
      "cue_infos": [
        {
          "SoundType": "EVGSoundType::WEAPON_SE",
          "CueId": 102,
          "CueName": "",
          "BlockIndex": 0,
          "Volume": 1.0,
          "Pitch": 0.0,
          "AisacParam": [],
          "IsStopForChangedAction": false,
          "IsReportPlayEnd": false,
          "IsPhysicalSurface": false,
          "IsPitchChangeByScale": false,
          "CueSheetIndex": 0
        }
      ],
      "is_attach": true,
      "node_name": "b_C_Base"
    }
  },
  {
    "Type": "VGANPlaySound",
    "Name": "VGANPlaySound_0",
    "Outer": "VGActionEvent_67",
    "Class": "UScriptClass'VGANPlaySound'",
    "Properties": {
      "cue_infos": [
        {
          "SoundType": "EVGSoundType::COMPONENT_VOICE",
          "CueId": 6200,
          "CueName": "",
          "BlockIndex": 0,
          "Volume": 1.0,
          "Pitch": 0.0,
          "AisacParam": [],
          "IsStopForChangedAction": false,
          "IsReportPlayEnd": false,
          "IsPhysicalSurface": false,
          "IsPitchChangeByScale": false,
          "CueSheetIndex": 0
        }
      ],
      "is_attach": true,
      "node_name": "b_C_Base"
    }
  },
  {
    "Type": "VGANPlaySound",
    "Name": "VGANPlaySound_0",
    "Outer": "VGActionEvent_9",
    "Class": "UScriptClass'VGANPlaySound'",
    "Properties": {
      "cue_infos": [
        {
          "SoundType": "EVGSoundType::WEAPON_SE",
          "CueId": 104,
          "CueName": "",
          "BlockIndex": 0,
          "Volume": 1.0,
          "Pitch": 0.0,
          "AisacParam": [],
          "IsStopForChangedAction": false,
          "IsReportPlayEnd": false,
          "IsPhysicalSurface": false,
          "IsPitchChangeByScale": false,
          "CueSheetIndex": 0
        }
      ],
      "is_attach": true,
      "node_name": "b_C_Base"
    }
  },
  {
    "Type": "VGANSActionBranch",
    "Name": "VGANSActionBranch_0",
    "Outer": "VGActionEvent_1",
    "Class": "UScriptClass'VGANSActionBranch'",
    "Properties": {
      "type": "EVGActionBranch::FloorHit",
      "action_id": 12050,
      "floor_check_distance": 40.0
    }
  },
  {
    "Type": "VGANSActionBranch",
    "Name": "VGANSActionBranch_0",
    "Outer": "VGActionEvent_45",
    "Class": "UScriptClass'VGANSActionBranch'",
    "Properties": {
      "action_id": 12
    }
  },
  {
    "Type": "VGANSActionBranch",
    "Name": "VGANSActionBranch_1",
    "Outer": "VGActionEvent_48",
    "Class": "UScriptClass'VGANSActionBranch'",
    "Properties": {
      "type": "EVGActionBranch::Landing",
      "action_id": 11
    }
  },
  {
    "Type": "VGANSActionMovement",
    "Name": "VGANSActionMovement_0",
    "Outer": "VGActionEvent_38",
    "Class": "UScriptClass'VGANSActionMovement'",
    "Properties": {
      "move_value": {
        "X": 0.0,
        "Y": 0.0,
        "Z": -500.0
      },
      "is_reset": false
    }
  },
  {
    "Type": "VGANSActionMovement",
    "Name": "VGANSActionMovement_0",
    "Outer": "VGActionEvent_39",
    "Class": "UScriptClass'VGANSActionMovement'",
    "Properties": {
      "move_op": "EVGActMoveOp::Attenuation",
      "move_value": {
        "X": 0.0,
        "Y": 0.0,
        "Z": 15.0
      }
    }
  },
  {
    "Type": "VGANSActionMovement",
    "Name": "VGANSActionMovement_0",
    "Outer": "VGActionEvent_43",
    "Class": "UScriptClass'VGANSActionMovement'",
    "Properties": {
      "move_value": {
        "X": 150.0,
        "Y": 0.0,
        "Z": 1750.0
      }
    }
  },
  {
    "Type": "VGANSActionState",
    "Name": "VGANSActionState_0",
    "Outer": "VGActionEvent_15",
    "Class": "UScriptClass'VGANSActionState'",
    "Properties": {
      "state_codes": [
        40
      ]
    }
  },
  {
    "Type": "VGANSActionState",
    "Name": "VGANSActionState_0",
    "Outer": "VGActionEvent_3",
    "Class": "UScriptClass'VGANSActionState'",
    "Properties": {
      "state_codes": [
        42,
        0
      ]
    }
  },
  {
    "Type": "VGANSActionState",
    "Name": "VGANSActionState_0",
    "Outer": "VGActionEvent_46",
    "Class": "UScriptClass'VGANSActionState'",
    "Properties": {
      "state_codes": [
        41
      ]
    }
  },
  {
    "Type": "VGANSignalVfx",
    "Name": "VGANSignalVfx_0",
    "Outer": "VGActionEvent_22",
    "Class": "UScriptClass'VGANSignalVfx'",
    "Properties": {
      "asset": {
        "ObjectName": "VGVfxSignalAsset'efs_WEP_Locus_Slash01_bl'",
        "ObjectPath": "/Game/Product/VFX_seven/VfxSignal/Chara/efs_WEP_Locus_Slash01_bl.0"
      },
      "location_offset": {
        "X": 0.0,
        "Y": 0.0,
        "Z": 80.0
      },
      "rotation_offset": {
        "Pitch": -85.0,
        "Yaw": 0.0,
        "Roll": 0.0
      },
      "scale_offset": {
        "X": 0.75,
        "Y": 0.75,
        "Z": 0.75
      }
    }
  },
  {
    "Type": "VGANSignalVfx",
    "Name": "VGANSignalVfx_0",
    "Outer": "VGActionEvent_23",
    "Class": "UScriptClass'VGANSignalVfx'",
    "Properties": {
      "asset": {
        "ObjectName": "VGVfxSignalAsset'efs_WEP_Locus_Slash01_bl_thin'",
        "ObjectPath": "/Game/Product/VFX_seven/VfxSignal/Chara/efs_WEP_Locus_Slash01_bl_thin.0"
      },
      "location_offset": {
        "X": 0.0,
        "Y": 0.0,
        "Z": 90.0
      },
      "rotation_offset": {
        "Pitch": -75.0,
        "Yaw": 30.0,
        "Roll": 180.0
      },
      "scale_offset": {
        "X": 0.75,
        "Y": 0.75,
        "Z": 0.75
      }
    }
  },
  {
    "Type": "VGANSignalVfx",
    "Name": "VGANSignalVfx_0",
    "Outer": "VGActionEvent_44",
    "Class": "UScriptClass'VGANSignalVfx'",
    "Properties": {
      "asset": {
        "ObjectName": "VGVfxSignalAsset'efs_WEP_SkillSlash01_bl_m'",
        "ObjectPath": "/Game/Product/VFX_seven/VfxSignal/Chara/efs_WEP_SkillSlash01_bl_m.0"
      },
      "location_offset": {
        "X": 0.0,
        "Y": 150.0,
        "Z": 150.0
      },
      "rotation_offset": {
        "Pitch": -170.0,
        "Yaw": 0.0,
        "Roll": -5.0
      }
    }
  },
  {
    "Type": "VGANSWeaponAttack",
    "Name": "VGANSWeaponAttack_0",
    "Outer": "VGActionEvent_19",
    "Class": "UScriptClass'VGANSWeaponAttack'",
    "Properties": {
      "node": "b_C_base",
      "position": {
        "X": 0.0,
        "Y": -50.0,
        "Z": 20.0
      },
      "rotation": {
        "Pitch": 0.0,
        "Yaw": -5.0,
        "Roll": 0.0
      },
      "desc": {
        "damage": 1.5,
        "attr": [
          "EVGDamageAttr::EVGDamageAttr_MAX",
          "EVGDamageAttr::Melee"
        ],
        "impact": "ESGDamageImpact::High",
        "burst_damage": 2.0,
        "hit_stop": 0.03,
        "owner_hit_stop": 0.01,
        "knock_back": {
          "factor": "EVGKnockBackFactor::AttackerDirection",
          "velocity": {
            "X": 300.0,
            "Y": 0.0,
            "Z": 0.0
          }
        },
        "damage_hate": 504.0,
        "hit_hate": -504.0,
        "reaction_value": 3.0,
        "hit_cam_shake": 4,
        "hit_force_feedback": 1
      },
      "melee_hit_effect_type": "ESGMeleeHitEffectType::Slash_M",
      "slash_direction": 90.0,
      "box_half_extent_x": 180.0,
      "box_half_extent_y": 70.0,
      "box_half_extent_z": 180.0
    }
  },
  {
    "Type": "VGANSWeaponAttack",
    "Name": "VGANSWeaponAttack_0",
    "Outer": "VGActionEvent_21",
    "Class": "UScriptClass'VGANSWeaponAttack'",
    "Properties": {
      "node": "b_C_base",
      "position": {
        "X": 0.0,
        "Y": -150.0,
        "Z": 160.0
      },
      "rotation": {
        "Pitch": 0.0,
        "Yaw": -10.0,
        "Roll": 0.0
      },
      "desc": {
        "damage": 1.6,
        "attr": [
          "EVGDamageAttr::EVGDamageAttr_MAX",
          "EVGDamageAttr::Melee"
        ],
        "impact": "ESGDamageImpact::Upper",
        "burst_damage": 2.0,
        "owner_hit_stop": 0.02,
        "knock_back": {
          "factor": "EVGKnockBackFactor::AttackerDirection",
          "rotation": "EVGKnockBackRotation::FrontFace",
          "velocity": {
            "X": 400.0,
            "Y": 0.0,
            "Z": 1200.0
          }
        },
        "damage_hate": 504.0,
        "hit_hate": -504.0,
        "reaction_value": 3.0,
        "hit_cam_shake": 4,
        "hit_force_feedback": 1
      },
      "melee_hit_effect_type": "ESGMeleeHitEffectType::Slash_L",
      "slash_direction": -10.0,
      "box_half_extent_x": 90.0,
      "box_half_extent_y": 250.0,
      "box_half_extent_z": 130.0
    }
  }
]