[
  {
    "Type": "AnimMontage",
    "Name": "MNT_AU_SMG_LinkArts_Homing",
    "Class": "UScriptClass'AnimMontage'",
    "Properties": {
      "BlendIn": {
        "BlendTime": 0.1
      },
      "BlendOut": {
        "BlendTime": 0.05
      },
      "BlendOutTriggerTime": 0.1,
      "CompositeSections": [
        {
          "SectionName": "Default",
          "NextSectionName": "Loop",
          "MetaData": [],
          "LinkedMontage": {
            "ObjectName": "AnimMontage'MNT_AU_SMG_LinkArts_Homing'",
            "ObjectPath": "/Game/Product/Character/Human/Common/Animation/Montage/SMG/MNT_AU_SMG_LinkArts_Homing.0"
          },
          "SlotIndex": 0,
          "SegmentIndex": 0,
          "LinkMethod": "EAnimLinkMethod::Absolute",
          "CachedLinkMethod": "EAnimLinkMethod::Absolute",
          "SegmentBeginTime": 0.0,
          "SegmentLength": 0.71428573,
          "LinkValue": 0.0,
          "LinkedSequence": {
            "ObjectName": "AnimSequence'AF_SMG_SKL_005_DLOOP'",
            "ObjectPath": "/Game/Product/AnimSequence/Human/AF/SMG/AF_SMG_SKL_005_DLOOP.0"
          }
        }
      ],
      "SlotAnimTracks": [
        {
          "SlotName": "DefaultSlot",
          "AnimTrack": {
            "AnimSegments": [
              {
                "AnimReference": {
                  "ObjectName": "AnimSequence'AF_SMG_SKL_005_DLOOP'",
                  "ObjectPath": "/Game/Product/AnimSequence/Human/AF/SMG/AF_SMG_SKL_005_DLOOP.0"
                },
                "StartPos": 0.0,
                "AnimStartTime": 0.0,
                "AnimEndTime": 0.5,
                "AnimPlayRate": 0.7,
                "LoopingCount": 1
              }
            ]
          }
        }
      ],
      "SequenceLength": 0.71428573,
      "Skeleton": {
        "ObjectName": "Skeleton'SKL_Human_00'",
        "ObjectPath": "/Game/Product/Character/Human/Common/Model/SKL_Human_00.29"
      }
    },
    "SkeletonGuid": "3F755F6B-47B4D3CB-A3CFE2BE-17F1853C"
  }
]