[
  {
    "Type": "DataTable",
    "Name": "ACCO_126_001",
    "Class": "UScriptClass'DataTable'",
    "Properties": {
      "RowStruct": {
        "ObjectName": "Class'SGAvatarAccessoryOffsetDataRow'",
        "ObjectPath": "/Script/SEVEN_Product"
      }
    },
    "Rows": {
      "1": {
        "mesh": {
          "AssetPathName": "/Game/Product/Character/Human/Common/Model/Male/Face/AM_FACE_002_000/Mesh/SKM_AM_FACE_002_000.SKM_AM_FACE_002_000",
          "SubPathString": ""
        },
        "location": {
          "X": 0.0,
          "Y": 0.0,
          "Z": 1.0
        },
        "rotation": {
          "Pitch": 0.0,
          "Yaw": 0.0,
          "Roll": 0.0
        },
        "scale": 0.85
      },
      "2": {
        "mesh": {
          "AssetPathName": "/Game/Product/Character/Human/Common/Model/Male/Face/AM_FACE_005_000/Mesh/SKM_AM_FACE_005_000.SKM_AM_FACE_005_000",
          "SubPathString": ""
        },
        "location": {
          "X": 0.0,
          "Y": 1.0,
          "Z": 0.5
        },
        "rotation": {
          "Pitch": 0.0,
          "Yaw": 0.0,
          "Roll": 0.0
        },
        "scale": 0.75
      },
      "3": {
        "mesh": {
          "AssetPathName": "/Game/Product/Character/Human/Common/Model/Female/Hair/AF_HAIR_007_000/Mesh/SKM_AF_HAIR_007_000.SKM_AF_HAIR_007_000",
          "SubPathString": ""
        },
        "location": {
          "X": 0.0,
          "Y": 0.5,
          "Z": 0.0
        },
        "rotation": {
          "Pitch": 0.0,
          "Yaw": 0.0,
          "Roll": 0.0
        },
        "scale": 1.0
      },
      "4": {
        "mesh": {
          "AssetPathName": "/Game/Product/Character/Human/Common/Model/Female/Hair/AF_HAIR_009_000/Mesh/SKM_AF_HAIR_009_000.SKM_AF_HAIR_009_000",
          "SubPathString": ""
        },
        "location": {
          "X": 0.0,
          "Y": 0.5,
          "Z": 0.0
        },
        "rotation": {
          "Pitch": 0.0,
          "Yaw": 0.0,
          "Roll": 0.0
        },
        "scale": 1.0
      },
      "5": {
        "mesh": {
          "AssetPathName": "/Game/Product/Character/Human/Common/Model/Female/Hair/AF_HAIR_010_000/Mesh/SKM_AF_HAIR_010_000.SKM_AF_HAIR_010_000",
          "SubPathString": ""
        },
        "location": {
          "X": 0.0,
          "Y": 0.5,
          "Z": 0.0
        },
        "rotation": {
          "Pitch": 0.0,
          "Yaw": 0.0,
          "Roll": 0.0
        },
        "scale": 1.0
      },
      "6": {
        "mesh": {
          "AssetPathName": "/Game/Product/Character/Human/Common/Model/Female/Hair/AF_HAIR_011_000/Mesh/SKM_AF_HAIR_011_000.SKM_AF_HAIR_011_000",
          "SubPathString": ""
        },
        "location": {
          "X": 0.0,
          "Y": 0.5,
          "Z": 0.0
        },
        "rotation": {
          "Pitch": 0.0,
          "Yaw": 0.0,
          "Roll": 0.0
        },
        "scale": 1.0
      },
      "7": {
        "mesh": {
          "AssetPathName": "/Game/Product/Character/Human/Common/Model/Female/Hair/AF_HAIR_017_000/Mesh/SKM_AF_HAIR_017_000.SKM_AF_HAIR_017_000",
          "SubPathString": ""
        },
        "location": {
          "X": 0.0,
          "Y": 0.0,
          "Z": 0.0
        },
        "rotation": {
          "Pitch": 0.0,
          "Yaw": 0.0,
          "Roll": 0.0
        },
        "scale": 1.02
      },
      "8": {
        "mesh": {
          "AssetPathName": "/Game/Product/Character/Human/Common/Model/Male/Hair/AM_HAIR_000_000/Mesh/SKM_AM_HAIR_000_000.SKM_AM_HAIR_000_000",
          "SubPathString": ""
        },
        "location": {
          "X": 0.0,
          "Y": 0.0,
          "Z": 0.0
        },
        "rotation": {
          "Pitch": 0.0,
          "Yaw": 0.0,
          "Roll": 0.0
        },
        "scale": 1.01
      },
      "9": {
        "mesh": {
          "AssetPathName": "/Game/Product/Character/Human/Common/Model/Male/Hair/AM_HAIR_003_000/Mesh/SKM_AM_HAIR_003_000.SKM_AM_HAIR_003_000",
          "SubPathString": ""
        },
        "location": {
          "X": 0.0,
          "Y": 0.0,
          "Z": 0.0
        },
        "rotation": {
          "Pitch": 0.0,
          "Yaw": 0.0,
          "Roll": 0.0
        },
        "scale": 1.01
      }
    }
  }
]